README.rst
setup.py
ringplus/__init__.py
ringplus/api.py
ringplus/auth.py
ringplus/binder.py
ringplus/error.py
ringplus/models.py
ringplus/parsers.py
ringplus/utils.py
ringplus.egg-info/PKG-INFO
ringplus.egg-info/SOURCES.txt
ringplus.egg-info/dependency_links.txt
ringplus.egg-info/requires.txt
ringplus.egg-info/top_level.txt
ringplus.egg-info/zip-safe