Metadata-Version: 1.1
Name: ringplus
Version: 0.1.0
Summary: RingPlus API library for python
Home-page: https://github.com/Shatnerz/ringplus
Author: shatnerz
Author-email: andrew.ahlers@gmail.com
License: MIT
Keywords: ringplus library
Platform: UNKNOWN
Classifier: Development Status :: 4 - Beta
Classifier: Topic :: Software Development :: Libraries
Classifier: License :: OSI Approved :: MIT License
Classifier: Operating System :: OS Independent
Classifier: Programming Language :: Python
Classifier: Programming Language :: Python :: 2
Classifier: Programming Language :: Python :: 2.6
Classifier: Programming Language :: Python :: 2.7
Classifier: Programming Language :: Python :: 3
Classifier: Programming Language :: Python :: 3.3
Classifier: Programming Language :: Python :: 3.4
